mqttcommander/Helper.py
mqttcommander/__init__.py
mqttcommander/cli.py
mqttcommander/models.py
mqttcommander/py.typed
mqttcommander/tasmotacommander.py
mqttcommander-0.0.4.dist-info/METADATA
mqttcommander-0.0.4.dist-info/WHEEL
mqttcommander-0.0.4.dist-info/entry_points.txt
mqttcommander-0.0.4.dist-info/licenses/LICENSE.md
mqttcommander-0.0.4.dist-info/RECORD
