Metadata-Version: 2.4
Name: mqttcommander
Version: 0.0.4
Summary: MQTTCommander
Project-URL: Homepage, https://github.com/vroomfondel/mqttcommander
Project-URL: Repository, https://github.com/vroomfondel/mqttcommander
Project-URL: Issues, https://github.com/vroomfondel/mqttcommander/issues
Author-email: Henning Thieß <ht@xomox.cc>
License-File: LICENSE.md
Keywords: command sender,home automation,iot,mqtt,mqtt client,tasmota
Classifier: Development Status :: 4 - Beta
Classifier: License :: OSI Approved :: GNU Lesser General Public License v3 or later (LGPLv3+)
Classifier: Operating System :: OS Independent
Classifier: Programming Language :: Python :: 3
Classifier: Programming Language :: Python :: 3.14
Classifier: Programming Language :: Python :: 3.15
Classifier: Topic :: Home Automation
Classifier: Topic :: Internet
Classifier: Topic :: Software Development :: Libraries
Classifier: Topic :: Software Development :: Libraries :: Python Modules
Requires-Python: >=3.14
Requires-Dist: loguru>=0.7.3
Requires-Dist: mqttstuff>=0.0.4
Requires-Dist: pydantic-extra-types>=2.10.2
Requires-Dist: pydantic-settings>=2.11.0
Requires-Dist: pydantic>=2.11.0
Requires-Dist: pytz>=2025.2
Requires-Dist: pyyaml>=6.0.0
